cmk_dev/__init__.py
cmk_dev/activity_from_fs.py
cmk_dev/binreplace.py
cmk_dev/check_rpath.py
cmk_dev/ci_artifacts.py
cmk_dev/cli.py
cmk_dev/cpumon.py
cmk_dev/decent_output.py
cmk_dev/jenkins_utils/__init__.py
cmk_dev/job_resource_usage.py
cmk_dev/last_access.py
cmk_dev/lockable_resources.py
cmk_dev/procmon.py
cmk_dev/pycinfo.py
cmk_dev/utils.py
cmk_dev/version.py
checkmk_dev_tools-2.0.2.dist-info/METADATA
checkmk_dev_tools-2.0.2.dist-info/WHEEL
checkmk_dev_tools-2.0.2.dist-info/entry_points.txt
checkmk_dev_tools-2.0.2.dist-info/RECORD
