Metadata-Version: 2.1
Name: checkmk-dev-tools
Version: 2.0.2
Summary: Checkmk DevOps tools
Author: Frans Fürst
Author-email: frans.fuerst@checkmk.com
Requires-Python: >=3.10.4,<4.0.0
Classifier: Programming Language :: Python :: 3
Classifier: Programming Language :: Python :: 3.11
Classifier: Programming Language :: Python :: 3.12
Classifier: Programming Language :: Python :: 3.13
Requires-Dist: influxdb-client (>=1,<2)
Requires-Dist: pydantic (>=2,<3)
Requires-Dist: python-jenkins (>=1.8.3,<1.9.0)
Requires-Dist: rich
Requires-Dist: trickkiste (>=0.3.4,<0.4.0)
Project-URL: Changelog, https://github.com/Checkmk/checkmk-dev-tools/blob/release/2.0.2/changelog.md
Project-URL: Repository, https://github.com/Checkmk/checkmk-dev-tools
